{
    "/js/app.js": "/js/app.js",
    "/css/app.css": "/css/app.css",
    "/images/backgroud.png": "/images/backgroud.png",
    "/images/banner.png": "/images/banner.png",
    "/images/bannerhome.png": "/images/bannerhome.png",
    "/images/CSS.png": "/images/CSS.png",
    "/images/face.png": "/images/face.png",
    "/images/Group.png": "/images/Group.png",
    "/images/Hapo_Learn_banner 1.png": "/images/Hapo_Learn_banner 1.png",
    "/images/hapo_white.png": "/images/hapo_white.png",
    "/images/java 1.png": "/images/java 1.png",
    "/images/js.png": "/images/js.png",
    "/images/laptop.png": "/images/laptop.png",
    "/images/laravel.png": "/images/laravel.png",
    "/images/logo.png": "/images/logo.png",
    "/images/php.png": "/images/php.png",
    "/images/Rec24.png": "/images/Rec24.png",
    "/fonts/utm_bryantlg-webfont.woff": "/fonts/utm_bryantlg-webfont.woff",
    "/fonts/utm_bryantlg-webfont.woff2": "/fonts/utm_bryantlg-webfont.woff2",
    "/fonts/UTM_BryantLG.ttf": "/fonts/UTM_BryantLG.ttf",
    "/fonts/UTM_BryantLG_B.ttf": "/fonts/UTM_BryantLG_B.ttf"
}
